xc/__init__.py
xc/__main__.py
xc/derived_data_clearner.py
xc/logger.py
xc/utils.py
xc/version_check.py
xc/xc.py
xcode_toolbox-1.3.1.dist-info/LICENSE
xcode_toolbox-1.3.1.dist-info/METADATA
xcode_toolbox-1.3.1.dist-info/WHEEL
xcode_toolbox-1.3.1.dist-info/entry_points.txt
xcode_toolbox-1.3.1.dist-info/top_level.txt
xcode_toolbox-1.3.1.dist-info/RECORD
