Metadata-Version: 2.1
Name: xcode-toolbox
Version: 1.3.1
Summary: A CLI tool which aims to provide a convenient operation toolbox on XCode project. You can use it to:(1) open XCode project or workspace. (2) remove project's derived data.(3) [WIP] force kill XCode process. (4) [WIP] generate Objective-C function signatures.
Home-page: https://github.com/zlrs/xcode-opener
Author: zlrs
Author-email: zhuys123@gmail.com
License: MIT
Platform: macOS
Requires-Dist: click (>=7.1.2)
Requires-Dist: requests (>=2.24.0)
